setup.py
tamme/__init__.py
tamme/tammecore.py
tamme_python.egg-info/PKG-INFO
tamme_python.egg-info/SOURCES.txt
tamme_python.egg-info/dependency_links.txt
tamme_python.egg-info/not-zip-safe
tamme_python.egg-info/requires.txt
tamme_python.egg-info/top_level.txt