Metadata-Version: 1.0
Name: tamme-python
Version: 0.8
Summary: A library for importing and installing tamme analytics from PyPi
Home-page: https://bitbucket.org/tamme-io/tamme-python
Author: tamme
Author-email: opensource@tamme.io
License: MIT
Platform: UNKNOWN
